SimpleITK/SimpleITK.py
SimpleITK/_SimpleITK.cpython-313-darwin.so
SimpleITK/__init__.py
SimpleITK/_version.py
SimpleITK/extra.py
SimpleITK/py.typed
SimpleITK_SimpleElastix-2.5.0.dev49.dist-info/LICENSE
SimpleITK_SimpleElastix-2.5.0.dev49.dist-info/METADATA
SimpleITK_SimpleElastix-2.5.0.dev49.dist-info/NOTICE
SimpleITK_SimpleElastix-2.5.0.dev49.dist-info/WHEEL
SimpleITK_SimpleElastix-2.5.0.dev49.dist-info/top_level.txt
SimpleITK_SimpleElastix-2.5.0.dev49.dist-info/RECORD
