Metadata-Version: 2.1
Name: SimpleITK-SimpleElastix
Version: 2.5.0.dev49
Summary: SimpleITK is a simplified interface to the Insight Toolkit (ITK) for image registration and segmentation
Home-page: http://simpleitk.org/
Author: Insight Software Consortium
Author-email: insight-users@itk.org
License: Apache
Project-URL: Bug Tracker, https://github.com/SimpleITK/SimpleITK/issues
Project-URL: Documentation, https://simpleitk.readthedocs.io/en/release/
Project-URL: Source Code, https://github.com/SimpleITK/SimpleITK
Keywords: SimpleITK ITK InsightToolkit segmentation registration
Classifier: License :: OSI Approved :: Apache Software License
Classifier: Programming Language :: Python
Classifier: Programming Language :: C++
Classifier: Development Status :: 5 - Production/Stable
Classifier: Intended Audience :: Education
Classifier: Intended Audience :: Healthcare Industry
Classifier: Intended Audience :: Science/Research
Classifier: Topic :: Scientific/Engineering
Classifier: Topic :: Scientific/Engineering :: Medical Science Apps.
Classifier: Topic :: Scientific/Engineering :: Information Analysis
Classifier: Topic :: Software Development :: Libraries
Classifier: Operating System :: Microsoft :: Windows
Classifier: Operating System :: POSIX
Classifier: Operating System :: Unix
Classifier: Operating System :: MacOS
License-File: LICENSE
License-File: NOTICE
